mcp_server_tavily/__init__.py
mcp_server_tavily/__main__.py
mcp_server_tavily/server.py
mcp_tavily-0.1.10.dist-info/LICENSE
mcp_tavily-0.1.10.dist-info/METADATA
mcp_tavily-0.1.10.dist-info/WHEEL
mcp_tavily-0.1.10.dist-info/top_level.txt
mcp_tavily-0.1.10.dist-info/RECORD
